python_12_033_poetry/__init__.py
python_12_033_poetry/app.py
python_12_033_poetry-0.1.0.dist-info/METADATA
python_12_033_poetry-0.1.0.dist-info/WHEEL
python_12_033_poetry-0.1.0.dist-info/RECORD
