Metadata-Version: 2.1
Name: python-12-033-poetry
Version: 0.1.0
Summary: 
Author: Krzysztof
Author-email: programowanie.krzysiek@gmail.com
Requires-Python: >=3.11,<4.0
Classifier: Programming Language :: Python :: 3
Classifier: Programming Language :: Python :: 3.11
Requires-Dist: flask (>=2.3.2,<3.0.0)
